{
  "version": "5.2.1",
  "flags": {},
  "shapes": [
    {
      "label": "lettuce",
      "points": [
        [
          188.4,
          51.2
        ],
        [
          193.1,
          46.4
        ],
        [
          202.7,
          42.5
        ],
        [
          213.3,
          40.5
        ],
        [
          221.4,
          38.3
        ],
        [
          228.6,
          34.9
        ],
        [
          237.1,
          34.3
        ],
        [
          252.5,
          34.9
        ],
        [
          261.6,
          35.6
        ],
        [
          268.2,
          38.4
        ],
        [
          278.1,
          41.9
        ],
        [
          285.0,
          51.1
        ],
        [
          285.3,
          55.6
        ],
        [
          294.4,
          68.5
        ],
        [
          298.7,
          74.3
        ],
        [
          302.5,
          77.4
        ],
        [
          306.3,
          82.9
        ],
        [
          313.9,
          87.0
        ],
        [
          320.3,
          87.8
        ],
        [
          323.8,
          89.7
        ],
        [
          328.2,
          83.3
        ],
        [
          330.1,
          80.5
        ],
        [
          330.1,
          77.6
        ],
        [
          332.5,
          73.8
        ],
        [
          332.9,
          70.5
        ],
        [
          332.5,
          63.9
        ],
        [
          338.2,
          59.9
        ],
        [
          345.2,
          59.3
        ],
        [
          348.5,
          59.5
        ],
        [
          355.5,
          66.9
        ],
        [
          360.1,
          70.2
        ],
        [
          367.8,
          69.7
        ],
        [
          372.3,
          68.6
        ],
        [
          380.4,
          61.2
        ],
        [
          381.6,
          54.3
        ],
        [
          386.7,
          43.2
        ],
        [
          392.4,
          37.3
        ],
        [
          400.0,
          30.3
        ],
        [
          407.5,
          29.6
        ],
        [
          411.0,
          30.4
        ],
        [
          416.9,
          30.6
        ],
        [
          419.8,
          33.3
        ],
        [
          422.5,
          33.5
        ],
        [
          426.9,
          31.0
        ],
        [
          433.3,
          29.3
        ],
        [
          436.0,
          31.0
        ],
        [
          443.4,
          28.6
        ],
        [
          450.1,
          31.5
        ],
        [
          451.0,
          32.8
        ],
        [
          456.2,
          32.7
        ],
        [
          460.7,
          35.5
        ],
        [
          462.0,
          42.9
        ],
        [
          459.7,
          52.3
        ],
        [
          459.8,
          57.3
        ],
        [
          464.1,
          63.6
        ],
        [
          468.8,
          74.0
        ],
        [
          472.1,
          79.1
        ],
        [
          475.1,
          82.7
        ],
        [
          479.7,
          84.9
        ],
        [
          485.0,
          91.6
        ],
        [
          484.9,
          94.6
        ],
        [
          486.6,
          100.4
        ],
        [
          483.4,
          103.6
        ],
        [
          475.1,
          108.1
        ],
        [
          466.7,
          112.4
        ],
        [
          462.4,
          121.2
        ],
        [
          459.8,
          133.1
        ],
        [
          457.7,
          144.5
        ],
        [
          457.8,
          153.1
        ],
        [
          458.6,
          155.4
        ],
        [
          459.2,
          163.3
        ],
        [
          462.4,
          167.0
        ],
        [
          457.5,
          169.8
        ],
        [
          453.9,
          171.4
        ],
        [
          453.4,
          178.2
        ],
        [
          453.0,
          192.4
        ],
        [
          449.5,
          194.7
        ],
        [
          442.9,
          194.0
        ],
        [
          440.2,
          197.0
        ],
        [
          437.6,
          199.7
        ],
        [
          433.2,
          198.2
        ],
        [
          423.8,
          191.7
        ],
        [
          409.9,
          187.1
        ],
        [
          400.8,
          185.2
        ],
        [
          397.2,
          186.6
        ],
        [
          395.0,
          192.3
        ],
        [
          386.8,
          201.3
        ],
        [
          383.6,
          204.9
        ],
        [
          379.6,
          206.2
        ],
        [
          378.9,
          207.7
        ],
        [
          374.2,
          207.7
        ],
        [
          369.6,
          210.0
        ],
        [
          364.5,
          216.3
        ],
        [
          372.2,
          216.2
        ],
        [
          373.0,
          213.5
        ],
        [
          374.6,
          211.1
        ],
        [
          378.1,
          209.8
        ],
        [
          380.8,
          209.8
        ],
        [
          382.7,
          212.7
        ],
        [
          385.2,
          210.5
        ],
        [
          388.8,
          210.5
        ],
        [
          391.4,
          208.3
        ],
        [
          395.6,
          205.4
        ],
        [
          395.6,
          210.3
        ],
        [
          402.5,
          210.0
        ],
        [
          406.9,
          206.2
        ],
        [
          413.5,
          203.5
        ],
        [
          415.3,
          203.7
        ],
        [
          417.8,
          207.7
        ],
        [
          421.2,
          207.6
        ],
        [
          426.8,
          205.3
        ],
        [
          429.9,
          204.5
        ],
        [
          433.8,
          207.3
        ],
        [
          435.6,
          209.5
        ],
        [
          441.5,
          210.1
        ],
        [
          447.6,
          210.2
        ],
        [
          453.9,
          209.8
        ],
        [
          458.0,
          207.5
        ],
        [
          462.9,
          207.9
        ],
        [
          466.5,
          210.6
        ],
        [
          477.0,
          209.0
        ],
        [
          492.1,
          204.1
        ],
        [
          502.8,
          199.1
        ],
        [
          511.2,
          192.5
        ],
        [
          517.1,
          185.9
        ],
        [
          521.4,
          179.1
        ],
        [
          524.4,
          174.6
        ],
        [
          527.3,
          175.7
        ],
        [
          530.8,
          174.4
        ],
        [
          533.3,
          173.1
        ],
        [
          541.9,
          173.9
        ],
        [
          546.0,
          177.9
        ],
        [
          548.6,
          179.4
        ],
        [
          550.8,
          183.5
        ],
        [
          552.8,
          187.1
        ],
        [
          556.9,
          188.9
        ],
        [
          561.0,
          188.8
        ],
        [
          562.4,
          190.5
        ],
        [
          571.9,
          193.5
        ],
        [
          572.8,
          197.2
        ],
        [
          574.8,
          200.1
        ],
        [
          576.5,
          202.7
        ],
        [
          579.7,
          203.3
        ],
        [
          580.8,
          206.7
        ],
        [
          583.6,
          208.8
        ],
        [
          584.9,
          216.5
        ],
        [
          586.3,
          219.2
        ],
        [
          587.3,
          224.9
        ],
        [
          588.0,
          230.4
        ],
        [
          590.1,
          232.7
        ],
        [
          590.7,
          241.3
        ],
        [
          594.0,
          247.2
        ],
        [
          595.1,
          258.1
        ],
        [
          596.1,
          272.5
        ],
        [
          597.7,
          300.4
        ],
        [
          598.2,
          307.7
        ],
        [
          597.3,
          312.9
        ],
        [
          596.6,
          327.4
        ],
        [
          596.3,
          339.5
        ],
        [
          597.5,
          347.6
        ],
        [
          599.7,
          350.3
        ],
        [
          605.0,
          358.8
        ],
        [
          606.1,
          363.6
        ],
        [
          604.0,
          366.2
        ],
        [
          600.2,
          364.5
        ],
        [
          593.8,
          357.2
        ],
        [
          589.7,
          350.8
        ],
        [
          584.6,
          349.3
        ],
        [
          577.6,
          349.4
        ],
        [
          573.6,
          347.5
        ],
        [
          567.8,
          348.3
        ],
        [
          554.7,
          343.7
        ],
        [
          551.0,
          342.7
        ],
        [
          542.8,
          343.1
        ],
        [
          530.9,
          341.8
        ],
        [
          526.8,
          342.1
        ],
        [
          515.7,
          349.6
        ],
        [
          509.5,
          351.3
        ],
        [
          497.8,
          353.3
        ],
        [
          495.8,
          354.9
        ],
        [
          492.3,
          355.4
        ],
        [
          488.3,
          343.5
        ],
        [
          480.8,
          325.5
        ],
        [
          475.6,
          315.8
        ],
        [
          472.7,
          314.8
        ],
        [
          470.3,
          313.4
        ],
        [
          467.2,
          313.4
        ],
        [
          459.7,
          308.5
        ],
        [
          455.4,
          308.1
        ],
        [
          453.2,
          308.4
        ],
        [
          447.2,
          312.6
        ],
        [
          442.1,
          314.7
        ],
        [
          437.4,
          310.9
        ],
        [
          433.4,
          306.4
        ],
        [
          432.0,
          301.7
        ],
        [
          429.2,
          300.5
        ],
        [
          424.6,
          299.2
        ],
        [
          424.4,
          292.7
        ],
        [
          423.1,
          290.4
        ],
        [
          418.4,
          289.6
        ],
        [
          413.6,
          291.9
        ],
        [
          409.4,
          293.6
        ],
        [
          407.5,
          290.8
        ],
        [
          394.4,
          292.4
        ],
        [
          384.8,
          293.8
        ],
        [
          377.3,
          293.2
        ],
        [
          369.7,
          289.5
        ],
        [
          364.7,
          287.6
        ],
        [
          371.0,
          299.5
        ],
        [
          386.9,
          314.6
        ],
        [
          396.3,
          321.2
        ],
        [
          405.0,
          325.6
        ],
        [
          403.7,
          331.1
        ],
        [
          405.1,
          342.0
        ],
        [
          406.3,
          344.7
        ],
        [
          406.0,
          354.7
        ],
        [
          401.7,
          361.3
        ],
        [
          397.5,
          365.6
        ],
        [
          392.1,
          371.6
        ],
        [
          388.8,
          373.9
        ],
        [
          383.3,
          380.0
        ],
        [
          377.2,
          385.3
        ],
        [
          373.8,
          387.4
        ],
        [
          369.6,
          388.6
        ],
        [
          361.5,
          390.7
        ],
        [
          351.0,
          393.8
        ],
        [
          341.7,
          395.5
        ],
        [
          341.8,
          402.0
        ],
        [
          340.0,
          414.6
        ],
        [
          337.4,
          418.1
        ],
        [
          334.7,
          425.7
        ],
        [
          327.7,
          430.1
        ],
        [
          323.9,
          433.7
        ],
        [
          319.9,
          437.7
        ],
        [
          313.3,
          439.4
        ],
        [
          309.8,
          446.6
        ],
        [
          299.3,
          456.0
        ],
        [
          293.1,
          457.5
        ],
        [
          288.2,
          462.5
        ],
        [
          283.2,
          464.9
        ],
        [
          278.7,
          465.2
        ],
        [
          268.0,
          467.3
        ],
        [
          263.2,
          466.6
        ],
        [
          256.8,
          468.5
        ],
        [
          251.5,
          466.6
        ],
        [
          244.5,
          467.3
        ],
        [
          238.9,
          465.5
        ],
        [
          230.6,
          463.5
        ],
        [
          218.7,
          458.9
        ],
        [
          211.0,
          453.9
        ],
        [
          203.4,
          452.6
        ],
        [
          180.3,
          440.6
        ],
        [
          172.8,
          435.0
        ],
        [
          171.7,
          432.2
        ],
        [
          165.6,
          424.9
        ],
        [
          165.6,
          420.6
        ],
        [
          162.6,
          416.7
        ],
        [
          160.4,
          408.0
        ],
        [
          159.6,
          397.6
        ],
        [
          160.3,
          389.3
        ],
        [
          160.5,
          385.1
        ],
        [
          160.4,
          378.9
        ],
        [
          160.6,
          371.3
        ],
        [
          162.6,
          366.8
        ],
        [
          160.1,
          363.2
        ],
        [
          160.9,
          354.6
        ],
        [
          163.1,
          347.6
        ],
        [
          165.8,
          343.2
        ],
        [
          166.7,
          336.5
        ],
        [
          167.8,
          331.9
        ],
        [
          166.5,
          324.9
        ],
        [
          167.2,
          319.7
        ],
        [
          174.5,
          306.6
        ],
        [
          176.9,
          305.6
        ],
        [
          180.7,
          302.1
        ],
        [
          184.4,
          303.2
        ],
        [
          193.4,
          307.3
        ],
        [
          203.6,
          307.9
        ],
        [
          218.8,
          305.5
        ],
        [
          218.4,
          301.7
        ],
        [
          220.8,
          299.3
        ],
        [
          228.3,
          298.3
        ],
        [
          237.8,
          294.5
        ],
        [
          243.3,
          290.3
        ],
        [
          243.0,
          284.7
        ],
        [
          246.2,
          278.3
        ],
        [
          249.6,
          277.4
        ],
        [
          252.8,
          275.4
        ],
        [
          254.1,
          272.7
        ],
        [
          249.6,
          265.3
        ],
        [
          252.1,
          263.9
        ],
        [
          256.1,
          261.8
        ],
        [
          259.1,
          259.1
        ],
        [
          263.0,
          261.8
        ],
        [
          269.3,
          262.8
        ],
        [
          272.0,
          260.2
        ],
        [
          270.7,
          257.5
        ],
        [
          269.1,
          254.5
        ],
        [
          269.0,
          251.5
        ],
        [
          275.6,
          253.3
        ],
        [
          281.5,
          255.3
        ],
        [
          285.8,
          253.9
        ],
        [
          283.5,
          251.8
        ],
        [
          283.9,
          250.1
        ],
        [
          294.0,
          248.7
        ],
        [
          304.9,
          242.8
        ],
        [
          313.1,
          236.2
        ],
        [
          316.8,
          233.9
        ],
        [
          310.9,
          229.2
        ],
        [
          308.6,
          226.2
        ],
        [
          300.5,
          222.3
        ],
        [
          297.2,
          221.3
        ],
        [
          295.5,
          221.3
        ],
        [
          293.0,
          219.3
        ],
        [
          286.7,
          221.0
        ],
        [
          284.7,
          218.2
        ],
        [
          280.4,
          214.9
        ],
        [
          277.3,
          215.8
        ],
        [
          274.3,
          214.3
        ],
        [
          271.4,
          215.2
        ],
        [
          265.9,
          216.4
        ],
        [
          264.8,
          211.8
        ],
        [
          263.0,
          208.5
        ],
        [
          256.8,
          206.3
        ],
        [
          249.4,
          206.4
        ],
        [
          248.2,
          202.5
        ],
        [
          245.7,
          199.9
        ],
        [
          241.1,
          198.5
        ],
        [
          236.4,
          201.5
        ],
        [
          233.9,
          200.9
        ],
        [
          229.2,
          198.0
        ],
        [
          227.0,
          195.6
        ],
        [
          223.3,
          196.7
        ],
        [
          220.0,
          198.9
        ],
        [
          217.4,
          197.2
        ],
        [
          220.8,
          192.9
        ],
        [
          229.3,
          190.2
        ],
        [
          237.4,
          185.1
        ],
        [
          241.9,
          181.9
        ],
        [
          246.1,
          174.7
        ],
        [
          249.7,
          165.8
        ],
        [
          248.1,
          150.8
        ],
        [
          243.4,
          130.3
        ],
        [
          240.9,
          125.0
        ],
        [
          227.5,
          112.0
        ],
        [
          202.8,
          101.7
        ],
        [
          180.5,
          93.7
        ],
        [
          161.1,
          88.1
        ],
        [
          154.2,
          80.3
        ],
        [
          154.0,
          76.4
        ],
        [
          161.1,
          67.2
        ],
        [
          167.1,
          63.1
        ],
        [
          180.7,
          56.5
        ],
        [
          187.2,
          51.8
        ]
      ],
      "group_id": null,
      "description": "",
      "shape_type": "polygon",
      "flags": {}
    }
  ],
  "imagePath": "205.png",
  "imageData": null,
  "imageHeight": 519,
  "imageWidth": 696
}